{
  "format_version": "1.21.6",
  "ambientocclusion": false,
  "textures": {
    "particle": "redstonepp:block/coil",
    "base": "redstonepp:block/coil",
    "trim": "redstonepp:block/diode_trim_1",
    "stone": "block/smooth_stone",
    "torch": "block/redstone_torch_off"
  },
  "elements": [
    {
      "from": [0, 0, 0],
      "to": [16, 2, 16],
      "faces": {
        "north": {"uv": [0, 14, 16, 16], "texture": "#stone", "cullface": "north"},
        "east": {"uv": [0, 14, 16, 16], "texture": "#stone", "cullface": "east"},
        "south": {"uv": [0, 14, 16, 16], "texture": "#stone", "cullface": "south"},
        "west": {"uv": [0, 14, 16, 16], "texture": "#stone", "cullface": "west"},
        "up": {"uv": [0, 0, 16, 16], "texture": "#base"},
        "down": {"uv": [0, 0, 16, 16], "texture": "#stone", "cullface": "down"}
      }
    },
    {
      "from": [7, 2, 2],
      "to": [9, 7, 4],
      "faces": {
        "north": {"uv": [7, 6, 9, 11], "texture": "#torch"},
        "east": {"uv": [7, 6, 9, 11], "texture": "#torch"},
        "south": {"uv": [7, 6, 9, 11], "texture": "#torch"},
        "west": {"uv": [7, 6, 9, 11], "texture": "#torch"},
        "up": {"uv": [7, 6, 9, 8], "texture": "#torch"}
      }
    },
    {
      "from": [3, 2, 6],
      "to": [13, 4, 13],
      "faces": {
        "north": {"uv": [0, 7, 10, 9], "texture": "#trim"},
        "east": {"uv": [10, 0, 12, 7], "rotation": 90, "texture": "#trim"},
        "south": {"uv": [0, 7, 10, 9], "texture": "#trim"},
        "west": {"uv": [10, 0, 12, 7], "rotation": 90, "texture": "#trim"},
        "up": {"uv": [0, 0, 10, 7], "texture": "#trim"}
      }
    },
    {
      "from": [4, 4, 7],
      "to": [7, 6, 12],
      "faces": {
        "north": {"uv": [0, 14, 3, 16], "texture": "#trim"},
        "east": {"uv": [3, 9, 5, 14], "rotation": 90, "texture": "#trim"},
        "south": {"uv": [0, 14, 3, 16], "texture": "#trim"},
        "west": {"uv": [3, 9, 5, 14], "rotation": 90, "texture": "#trim"},
        "up": {"uv": [0, 9, 3, 14], "texture": "#trim"}
      }
    },
    {
      "from": [9, 4, 7],
      "to": [12, 6, 12],
      "faces": {
        "north": {"uv": [0, 14, 3, 16], "texture": "#trim"},
        "east": {"uv": [3, 9, 5, 14], "rotation": 90, "texture": "#trim"},
        "south": {"uv": [0, 14, 3, 16], "texture": "#trim"},
        "west": {"uv": [3, 9, 5, 14], "rotation": 90, "texture": "#trim"},
        "up": {"uv": [0, 9, 3, 14], "texture": "#trim"}
      }
    }
  ]
}